{
  "name": "Gabriel B Possomato",
  "photo": "https://avatars.githubusercontent.com/u/123518333?s=400&u=2a9502f45a57b204196218c290628a1a9e0b0934&v=4",
  "job": "Estudante",
  "location": "Iperó - SP",
  "phone": "15981273036",
  "mail": "gabrielb.possomato@gmail.com",
  "skills": {
    "hardSkills": [
      {
        "name": "JavaScript",
        "logo": "https://raw.githubusercontent.com/digitalinnovationone/js-developer-portfolio/main/data/imgs/js.png"
      },
      {
        "name": "Node",
        "logo": "https://raw.githubusercontent.com/digitalinnovationone/js-developer-portfolio/main/data/imgs/nodejs.png"
      },
      {
        "name": "HTML",
        "logo": "https://raw.githubusercontent.com/digitalinnovationone/js-developer-portfolio/main/data/imgs/html.png"
      },
      {
        "name": "CSS",
        "logo": "https://raw.githubusercontent.com/digitalinnovationone/js-developer-portfolio/main/data/imgs/css.png"
      }
    ],
    "softSkills": [
      "Facilidade com tarefas práticas",
      "Comunicação",
      "Trabalho em equipe",
      "Organização",
      "Compromentimento com resultados"
    ]
  },
  "education": [
    {
      "institution": "SENAI - Serviço Nacional de Aprendizagem Industrial",
      "course": "Técnico em Mecatrônica",
      "period": "2018 - 2020",
      "concluded": true
    },
    {
      "institution": "UNIVESP - Universidade Virtual do Estado de São Paulo",
      "course": "Engenharia de Computação",
      "period": "2022 - 2027",
      "concluded": false
    },
    {
      "institution": "UNINTER - Centro Universitário Internacional",
      "course": "Análise e Desenvolvimento de Sistemas",
      "period": "2023 - 2025",
      "concluded": false
    }
  ],
  "languages":[
    {
      "language": "Inglês",
      "level": "medio"
    },
    {
      "language": "Português",
      "level": "alto"
    },
    {
      "language": "Italiano",
      "level": "baixo"
    }
  ],
  "portfolio": [
    {
      "name": "Pokedex",
      "url": "https://github.com/Possomato/DIO/tree/main/javascript/Bootcamp-FormacaoJavaScriptDeveloper/modulo02/POKEDEX",
      "github": true
    },
    {
      "name": "Encomendas - @pupped.store",
      "url": "https://github.com/Possomato/pupped",
      "github": true
    },
    {
      "name": "Calculadora de IMC",
      "url": "https://github.com
